pf9_saml_auth/__init__.py
pf9_saml_auth/_loading.py
pf9_saml_auth/v3/__init__.py
pf9_saml_auth/v3/adfs.py
pf9_saml_auth/v3/base.py
pf9_saml_auth/v3/okta.py
pf9_saml_auth/v3/onelogin.py
pf9_saml_auth-0.0.2.dist-info/DESCRIPTION.rst
pf9_saml_auth-0.0.2.dist-info/METADATA
pf9_saml_auth-0.0.2.dist-info/RECORD
pf9_saml_auth-0.0.2.dist-info/WHEEL
pf9_saml_auth-0.0.2.dist-info/entry_points.txt
pf9_saml_auth-0.0.2.dist-info/metadata.json
pf9_saml_auth-0.0.2.dist-info/top_level.txt
