Metadata-Version: 2.0
Name: pf9-saml-auth
Version: 0.0.2
Summary: Platform9 SAML Authentication Library for OpenStack Identity
Home-page: https://github.com/platform9/pf9-saml-auth
Author: Blake Covarrubias
Author-email: blake@platform9.com
License: Apache License 2.0
Keywords: openstack keystone saml
Platform: UNKNOWN
Classifier: Development Status :: 3 - Alpha
Classifier: Environment :: OpenStack
Classifier: Intended Audience :: Developers
Classifier: Intended Audience :: System Administrators
Classifier: License :: OSI Approved :: Apache Software License
Classifier: Operating System :: POSIX :: Linux
Classifier: Programming Language :: Python
Classifier: Programming Language :: Python :: 2
Classifier: Programming Language :: Python :: 2.7
Requires-Python: >=2.7, !=3.*
Requires-Dist: keystoneauth1
Requires-Dist: lxml
Requires-Dist: oktaauth
Requires-Dist: python-keystoneclient
